cditools/__init__.py
cditools/_version.py
cditools/_version.pyi
cditools/eiger.py
cditools/merlin.py
cditools/motors.py
cditools/py.typed
cditools/trigger_mixins.py
cditools/utils.py
cditools/simulated/__init__.py
cditools/simulated/black_hole.py
cditools-0.1.0.dist-info/licenses/LICENSE
cditools-0.1.0.dist-info/METADATA
cditools-0.1.0.dist-info/WHEEL
cditools-0.1.0.dist-info/entry_points.txt
cditools-0.1.0.dist-info/top_level.txt
cditools-0.1.0.dist-info/RECORD
